mpyll/__init__.py
mpyll/mpyll.py
mpyll-0.2.dist-info/LICENSE.txt
mpyll-0.2.dist-info/METADATA
mpyll-0.2.dist-info/WHEEL
mpyll-0.2.dist-info/top_level.txt
mpyll-0.2.dist-info/RECORD
