Metadata-Version: 2.1
Name: mpyll
Version: 0.2
Summary: A package for easy task parallelization across CPU threads
Home-page: https://gitlab.com/mhdy/mpyll
Author: Mehdi
Author-email: ydhm@protonmail.com
License: License :: OSI Approved :: GNU General Public License v3 (GPLv3)
Keywords: parallel parallelization multiprocessing
Platform: UNKNOWN
Classifier: Development Status :: 5 - Production/Stable
Classifier: Intended Audience :: Developers
Classifier: Intended Audience :: Science/Research
Classifier: License :: OSI Approved :: GNU General Public License v3 (GPLv3)
Classifier: Programming Language :: Python :: 3
Classifier: Operating System :: OS Independent
